jellyfaas/__init__.py
jellyfaas/ai_client.py
jellyfaas/ai_config.py
jellyfaas/ai_provider.py
jellyfaas/client.py
jellyfaas/config.py
jellyfaas/exceptions.py
jellyfaas/structs/__init__.py
jellyfaas/structs/function_requirements.py
jellyfaas-1.0.0.dist-info/METADATA
jellyfaas-1.0.0.dist-info/WHEEL
jellyfaas-1.0.0.dist-info/licenses/LICENSE
jellyfaas-1.0.0.dist-info/RECORD
