Metadata-Version: 2.3
Name: jellyfaas
Version: 1.0.0
Summary: A client for interacting with the JellyFaaS API
Project-URL: Source, https://github.com/platform48/python-sdk
Project-URL: Documentation, https://github.com/platform48/python-sdk/
Project-URL: Tracker, https://github.com/platform48/python-sdk/issues
Project-URL: Changelog, https://github.com/platform48/python-sdk/releases
Author-email: Platform48 <hello@platform48.com>, Caleb Hartshorn <caleb@platform48.com>
Maintainer-email: Platform48 <hello@platform48.com>, Caleb Hartshorn <caleb@platform48.com>
License: Copyright (c) 2024 Platform48
Keywords: API,FAAS,JellyFaaS,SDK,client,cloud functions
Classifier: Development Status :: 3 - Alpha
Classifier: Framework :: Pydantic
Classifier: License :: OSI Approved :: MIT License
Classifier: Natural Language :: English
Classifier: Programming Language :: Python :: 3
Requires-Dist: jsonschema
Requires-Dist: pydantic
Requires-Dist: requests
